sparkgrep/__init__.py
sparkgrep/check_spark_actions.py
sparkgrep/cli.py
sparkgrep/file_processors.py
sparkgrep/patterns.py
sparkgrep/utils.py
sparkgrep-0.1.1a1.dist-info/licenses/LICENSE
sparkgrep-0.1.1a1.dist-info/METADATA
sparkgrep-0.1.1a1.dist-info/WHEEL
sparkgrep-0.1.1a1.dist-info/entry_points.txt
sparkgrep-0.1.1a1.dist-info/top_level.txt
sparkgrep-0.1.1a1.dist-info/RECORD
