Metadata-Version: 2.4
Name: sparkgrep
Version: 0.1.1a1
Summary: Pre-commit hooks for Apache Spark development (Databricks, EMR, Dataproc, and more)
Author-email: Leandro Kellermann de Oliveira <lkellermann@leandroasaservice.com>
Maintainer-email: Leandro Kellermann de Oliveira <lkellermann@leandroasaservice.com>
License: MIT
Project-URL: Homepage, https://github.com/leandroasaservice/sparkgrep
Project-URL: Repository, https://github.com/leandroasaservice/sparkgrep
Project-URL: Documentation, https://github.com/leandroasaservice/sparkgrep/blob/main/README.md
Project-URL: Bug Reports, https://github.com/leandroasaservice/sparkgrep/issues
Project-URL: Source, https://github.com/leandroasaservice/sparkgrep
Project-URL: Contributing, https://github.com/leandroasaservice/sparkgrep/blob/main/doc/CONTRIBUTING.md
Keywords: spark,databricks,pre-commit,code-quality,linting
Classifier: Development Status :: 2 - Pre-Alpha
Classifier: Intended Audience :: Developers
Classifier: License :: OSI Approved :: MIT License
Classifier: Programming Language :: Python :: 3
Classifier: Programming Language :: Python :: 3.8
Classifier: Programming Language :: Python :: 3.9
Classifier: Programming Language :: Python :: 3.10
Classifier: Programming Language :: Python :: 3.11
Classifier: Programming Language :: Python :: 3.12
Classifier: Topic :: Software Development :: Quality Assurance
Classifier: Topic :: Software Development :: Libraries :: Python Modules
Requires-Python: >=3.8
License-File: LICENSE
Requires-Dist: pre-commit>=3.0.0
Requires-Dist: ruff>=0.1.0
Requires-Dist: nbformat>=5.0.0
Provides-Extra: dev
Requires-Dist: pytest>=7.0.0; extra == "dev"
Requires-Dist: pytest-cov>=4.0.0; extra == "dev"
Requires-Dist: pytest-mock>=3.10.0; extra == "dev"
Requires-Dist: coverage>=7.0.0; extra == "dev"
Requires-Dist: bandit>=1.7.0; extra == "dev"
Dynamic: license-file
